{"Easy":{"Reimu":[],"Marisa":[],"Sakuya":[{"id":13,"score":1324469560,"name":"JSMT","date":"2021-05-05"}],"Sanae":[{"id":4,"score":1242015760,"name":"CCO","date":"2021-05-07"},{"id":46,"score":1259125430,"name":"Mon3tr","date":"2021-05-08"}]},"Normal":{"Reimu":[{"id":47,"score":2671478280,"name":"ZY","date":"2021-05-06"},{"id":47,"score":2809325590,"name":"ZY","date":"2021-05-07"},{"id":47,"score":2958469850,"name":"ZY","date":"2021-05-08"},{"id":47,"score":3018519010,"name":"ZY","date":"2021-05-08"}],"Marisa":[{"id":6,"score":1414480220,"name":"YMD","date":"2021-05-04"}],"Sakuya":[{"id":12,"score":2633867280,"name":"Ｋ・Ｇ","date":"2021-05-04"},{"id":18,"score":4420225840,"name":"Crested","date":"2021-05-08"}],"Sanae":[{"id":4,"score":2697251860,"name":"CCO","date":"2021-05-07"},{"id":21,"score":4035749120,"name":"zvs","date":"2022-03-14"}]},"Hard":{"Reimu":[{"id":12,"score":1335287870,"name":"Ｋ・Ｇ","date":"2021-05-04"},{"id":48,"score":1895823940,"name":"Adam","date":"2021-05-04"},{"id":7,"score":3370950380,"name":"回虫","date":"2021-05-06"}],"Marisa":[],"Sakuya":[{"id":12,"score":5283669270,"name":"Ｋ・Ｇ","date":"2021-05-04"},{"id":23,"score":6214298650,"name":"EBM","date":"2021-05-07"},{"id":23,"score":7181683430,"name":"EBM","date":"2021-05-07"},{"id":23,"score":7736260710,"name":"EBM","date":"2021-05-07"}],"Sanae":[]},"Lunatic":{"Reimu":[],"Marisa":[],"Sakuya":[{"id":32,"score":15354077600,"name":"RB","date":"2023-08-10"},{"id":32,"score":16045229940,"name":"RB","date":"2023-08-10"}],"Sanae":[{"id":49,"score":5028911290,"name":"Weedy","date":"2021-05-04"},{"id":35,"score":6173974740,"name":"实况主本人","date":"2021-05-04"},{"id":35,"score":7405987950,"name":"实况主本人","date":"2021-05-07"},{"id":35,"score":7868142410,"name":"实况主本人","date":"2021-05-10"}]},"Extra":{"Reimu":[{"id":39,"score":1573827050,"name":"園田琴梨","date":"2021-05-05"}],"Marisa":[{"id":7,"score":1655200440,"name":"回虫","date":"2021-05-07"},{"id":29,"score":2859885880,"name":"idtn","date":"2021-08-19"}],"Sakuya":[{"id":45,"score":4999323010,"name":"Pearl","date":"2021-05-03"},{"id":41,"score":5455968010,"name":"すいれん","date":"2021-05-04"},{"id":41,"score":5587946940,"name":"すいれん","date":"2021-05-08"}],"Sanae":[{"id":7,"score":1626775850,"name":"回虫","date":"2021-05-05"}]}}